dtmf_py/__init__.py
dtmf_py/dtmf.py
dtmf_py-0.1.3.dist-info/LICENSE
dtmf_py-0.1.3.dist-info/METADATA
dtmf_py-0.1.3.dist-info/WHEEL
dtmf_py-0.1.3.dist-info/RECORD
