Metadata-Version: 2.1
Name: dtmf-py
Version: 0.1.3
Summary: DTMF (rfc2833) generator
Home-page: https://github.com/PesyCorm/dtmf_py
License: MIT
Author: Dmitriy Noskov
Author-email: pesycorm@yandex.ru
Requires-Python: >=3.8,<4.0
Classifier: License :: OSI Approved :: MIT License
Classifier: Programming Language :: Python :: 3
Classifier: Programming Language :: Python :: 3.8
Classifier: Programming Language :: Python :: 3.9
Classifier: Programming Language :: Python :: 3.10
Classifier: Programming Language :: Python :: 3.11
Classifier: Programming Language :: Python :: 3.12
Requires-Dist: rtp (>=0.0.4,<0.0.5)
Project-URL: Repository, https://github.com/PesyCorm/dtmf_py
